switch_activation.py
switch_activation-0.0.1.dist-info/LICENSE
switch_activation-0.0.1.dist-info/WHEEL
switch_activation-0.0.1.dist-info/METADATA
switch_activation-0.0.1.dist-info/RECORD
