Metadata-Version: 2.1
Name: switch_activation
Version: 0.0.1
Summary: A switch between several activation functions.
Author-email: Jorge Cardona <cardona@ukp.tu-darmstadt.de>
Classifier: License :: OSI Approved :: MIT License
Requires-Dist: torch
Requires-Dist: numpy
